<?xml version="1.0" encoding="utf-8"?>
<odoo>
    <data>

        <!-- SLIDE.CHANNEL VIEWS -->
        <record model="ir.ui.view" id="view_slide_channel_form">
            <field name="name">slide.channel.form</field>
            <field name="model">slide.channel</field>
            <field name="arch" type="xml">
                <form string="Channels">
                    <header>
                        <button name="action_channel_invite" string="Invite" type="object" class="oe_highlight"  attrs="{'invisible': [('enroll', '!=', 'invite')]}"/>
                    </header>
                    <sheet>
                        <div class="oe_button_box" name="button_box">
                            <button name="action_redirect_to_content"
                                type="object"
                                icon="fa-bars"
                                class="oe_stat_button"
                                groups="website.group_website_publisher">
                               <span class="o_stat_text">Content</span>
                            </button>
                            <button name="action_redirect_to_content"
                                type="object"
                                icon="fa-star"
                                class="oe_stat_button"
                                groups="website.group_website_publisher">
                                <field string="Reviews" name="rating_count" widget="statinfo"/>
                            </button>
                            <button name="action_redirect_to_members"
                                type="object"
                                icon="fa-users"
                                class="oe_stat_button"
                                groups="website.group_website_publisher">
                                <field name="members_count" string="Attendees" widget="statinfo"/>
                            </button>
                            <button class="oe_stat_button" name="website_publish_button"
                                    type="object" icon="fa-globe">
                                <field name="is_published" widget="website_button"/>
                            </button>
                            <button name="toggle_active" type="object" confirm="(Un)archiving a channel automatically (un)archives its slides. Do you want to proceed?" class="oe_stat_button" icon="fa-archive">
                                <field name="active" widget="boolean_button" options='{"terminology": "archive"}'/>
                            </button>
                        </div>
                        <field name="image" widget="image" class="oe_avatar" options="{'preview_image': 'image_medium'}"/>
                        <div class="oe_title">
                            <label for="name" class="oe_edit_only" string="Course Title"/>
                            <h1><field name="name" default_focus="1" placeholder="Course Title"/></h1>
                        </div>
                        <group>
                            <group>
                                <field name="tag_ids" widget="many2many_tags" placeholder="Tags"/>
                            </group>
                        </group>
                        <notebook colspan="4">
                            <page string="Content">
                                <field name="slide_ids" colspan="4" nolabel="1" widget="category_one2many">
                                     <tree decoration-bf="is_category"  editable="bottom">
                                        <field name="sequence" widget="handle"/>
                                        <field name="name"/>
                                        <field name="slide_type" attrs="{'invisible': [('slide_type', '=', 'category')]}"/>
                                        <field name="completion_time" attrs="{'invisible': [('slide_type', '=', 'category')]}"/>
                                        <field name="total_views" attrs="{'invisible': [('slide_type', '=', 'category')]}"/>
                                        <field name="is_category" invisible="1"/>

                                        <control>
                                            <create name="add_slide_section" string="Add Section" context="{'default_is_category': True, 'default_channel_id': active_id}"/>
                                            <create name="add_slide_lesson" string="Add Lesson" context="{'default_channel_id': active_id}"/>
                                        </control>
                                    </tree>
                                </field>
                            </page>
                            <page string="Description">
                                <field name="description" colspan="4" nolabel="1"/>
                            </page>
                            <page string="Options">
                                <group>
                                    <group string="Course">
                                        <field name="channel_type" widget="radio"/>
                                        <field name="user_id"/>
                                        <field name="website_id" options="{'no_create': True}" groups="website.group_multi_website"/>
                                        <!-- <field name="promote_strategy" widget="radio"/> -->
                                    </group>
                                    <group string="Access Rights">
                                        <field name="enroll" widget="radio" options="{'horizontal': true}"/>
                                        <field name="upload_group_ids" widget="many2many_tags"/>
                                        <field name="enroll_group_ids" widget="many2many_tags" groups="base.group_no_one"/>
                                    </group>
                                </group>
                                <group>
                                    <group string="Communication">
                                        <field name="allow_comment"/>
                                        <field name="publish_template_id" domain="[('model','=','slide.slide')]"/>
                                        <field name="share_template_id" domain="[('model','=','slide.slide')]"/>
                                    </group>
                                    <group string="Display">
                                        <field name="visibility" widget="radio"/>
                                        <field name="promote_strategy" widget="radio"/>
                                    </group>
                                </group>
                                <div attrs="{'invisible': [('enroll', '!=', 'invite')]}">
                                    <label for="enroll_msg"/>
                                    <field name="enroll_msg" colspan="4" nolabel="1"/>
                                </div>
                            </page>
                            <page string="Karma Rules" name="karma_rules">
                                <group>
                                    <field string="Rank Course" name="karma_gen_channel_rank"/>
                                    <field string="Finish Course" name="karma_gen_channel_finish"/>
                                    <field string="Add Review" name="karma_review" attrs="{'invisible': [('allow_comment', '!=', True)]}"/>
                                    <field string="Add Comment" name="karma_slide_comment" attrs="{'invisible': [('allow_comment', '!=', True)]}"/>
                                </group>
                            </page>
                            <page string="Statistics">
                                <group>
                                    <group class="col-4">
                                        <field name="nbr_presentation"/>
                                        <field name="nbr_document"/>
                                        <field name="nbr_video"/>
                                        <field name="nbr_infographic"/>
                                        <field name="nbr_webpage"/>
                                        <hr style="width=100%;background-color:rgb(204,204,204);border:medium none;clear:both;display:block;font-size:0px;min-height:1px;line-height:0; margin:10px -55px 16px 0px;"/>
                                        <field name="total_slides"/>
                                    </group>
                                    <group>
                                        <field name="total_views"/>
                                        <field string="Rating" name="total_votes"/>
                                        <label for="total_time" string="Watch Time"/>
                                        <div>
                                            <field name="total_time"/>
                                            <span class="ml-2">Hours</span>
                                        </div>
                                    </group>
                                </group>
                            </page>
                        </notebook>
                    </sheet>
                    <div class="oe_chatter">
                        <field name="message_follower_ids" widget="mail_followers"/>
                        <field name="message_ids" widget="mail_thread"/>
                    </div>
                </form>
            </field>
        </record>

        <record id="slide_channel_view_tree" model="ir.ui.view">
            <field name="name">slide.channel.tree</field>
            <field name="model">slide.channel</field>
            <field name="arch" type="xml">
                <tree string="Channel">
                    <field name="sequence" widget="handle"/>
                    <field name="name"/>
                    <field name="website_id" groups="website.group_multi_website"/>
                    <field name="active" invisible="1"/>
                    <field name="enroll"/>
                    <field name="promote_strategy"/>
                </tree>
            </field>
        </record>

        <record id="slide_channel_view_search" model="ir.ui.view">
            <field name="name">slide.channel.search</field>
            <field name="model">slide.channel</field>
            <field name="arch" type="xml">
                <search string="Courses">
                    <field name="name" string="Course"/>
                    <filter string="Archived" name="inactive" domain="[('active','=',False)]"/>
                </search>
            </field>
        </record>

        <record id="action_slide_channels" model="ir.actions.act_window">
            <field name="name">Channels</field>
            <field name="res_model">slide.channel</field>
            <field name="view_mode">tree,form</field>
            <field name="search_view_id" ref="website_slides.slide_channel_view_search"/>
            <field name="help" type="html">
                <p class="o_view_nocontent_smiling_face">
                    Create a channel
                </p>
            </field>
        </record>
    </data>
</odoo>
